README.md
setup.cfg
setup.py
ms_cv/__init__.py
ms_cv.egg-info/PKG-INFO
ms_cv.egg-info/SOURCES.txt
ms_cv.egg-info/dependency_links.txt
ms_cv.egg-info/top_level.txt