Metadata-Version: 1.1
Name: ms-cv
Version: 0.1.0
Summary: A correlation vector implementation in python
Home-page: https://github.com/OpenXbox/ms_cv
Author: OpenXbox
Author-email: noreply@openxbox.org
License: MIT
Platform: UNKNOWN
Classifier: Development Status :: 2 - Pre-Alpha
Classifier: License :: OSI Approved :: MIT License
Classifier: Programming Language :: Python
Classifier: Programming Language :: Python :: 3
Classifier: Programming Language :: Python :: 3.4
Classifier: Programming Language :: Python :: 3.5
Classifier: Programming Language :: Python :: 3.6
Classifier: Programming Language :: Python :: 3.7
